MANIFEST.in
README.md
setup.py
py/__init__.py
py/server.py
py/static/index.html
py/static/css/style.css
py/static/js/main.js
visdom.egg-info/PKG-INFO
visdom.egg-info/SOURCES.txt
visdom.egg-info/dependency_links.txt
visdom.egg-info/not-zip-safe
visdom.egg-info/requires.txt
visdom.egg-info/top_level.txt