Metadata-Version: 1.0
Name: visdom
Version: 0.1.7
Summary: A tool for visualizing live, rich data for Torch and Numpy
Home-page: https://github.com/facebookresearch/visdom
Author: Allan Jabri, Jack Urbanek
Author-email: jju@fb.com
License: CC-BY-4.0
Platform: UNKNOWN
